fifo/fifo.v
module fifo #(
    parameter DATA_WIDTH = 8,
    parameter FIFO_ASIZE = 4
)(
    input wire in_clock,
    input wire in_reset,
    input wire in_take,
    input wire in_put,
    output wire out_empty,
    output wire out_full,
    output wire [DATA_WIDTH-1:0] out_data,
    input wire [DATA_WIDTH-1:0] in_data
);
    wire [FIFO_ASIZE-1:0] write_address;
    wire [FIFO_ASIZE-1:0] read_address;

    fifo_controller controller(
        .in_clock(in_clock),
        .in_reset(in_reset),
        .in_put(in_put),
        .in_take(in_take),
        .out_empty(out_empty),
        .out_full(out_full),
        .out_read_pointer(read_address),
        .out_write_pointer(write_address)
    );

    reg [DATA_WIDTH-1:0] memory [0:(1<<FIFO_ASIZE)-1];
    reg [DATA_WIDTH-1:0] data;
    assign out_data = data;

    always @(posedge in_clock) begin
        if (in_reset) begin
            data <= 0;
        end
        else if (in_take && ~out_empty) begin
            data <= memory[read_address];
        end
        else begin
            data <= data;
        end
        if (in_put && ~out_full) begin
            memory[write_address] <= in_data;
        end

    end
endmodule

module fifo_controller #(
    parameter FIFO_ASIZE = 4
)(
    input wire in_clock,
    input wire in_reset,
    input wire in_take,
    input wire in_put,
    output wire out_empty,
    output wire out_full,
    output wire [FIFO_ASIZE-1:0] out_write_pointer,
    output wire [FIFO_ASIZE-1:0] out_read_pointer
);
    reg [FIFO_ASIZE:0] read_pointer;
    reg [FIFO_ASIZE:0] write_pointer; // write pointer can go back to begin when memory is full, then the extra bit indicates it went back

    assign out_write_pointer = write_pointer[FIFO_ASIZE-1:0];
    assign out_read_pointer  = read_pointer[FIFO_ASIZE-1:0];

    assign out_empty = (read_pointer == write_pointer); // read pointer catches write pointer, higher addresses are not written or already read, write is allowed
    assign out_full = (read_pointer[FIFO_ASIZE-1:0] == write_pointer[FIFO_ASIZE-1:0]) // read pointer went back to begin, so higher addresses are unread and cannot be overwritten
                && (read_pointer[FIFO_ASIZE] != write_pointer[FIFO_ASIZE]);

    always @(posedge in_clock) begin
        if (in_reset) begin // reset case
            read_pointer <= 0;
            write_pointer <= 0;
        end
        else begin
            if (out_empty) begin // empty case: only in_put or both is allowed
                if (in_put && ~in_take) begin
                    write_pointer <= write_pointer + 1;
                end
                else if (in_put && in_take) begin
                    write_pointer <= write_pointer + 1;
                    read_pointer <= read_pointer + 1;
                end
            end
            else if (out_full) begin // full case: only in_take or both is allowed
                if (in_take & ~in_put) begin 
                    read_pointer <= read_pointer + 1;
                end
                else if (in_put & in_take) begin
                    write_pointer <= write_pointer + 1;
                    read_pointer <= read_pointer + 1;
                end
            end
            else begin // normal case: everything is allowed
                if (in_take) begin
                    read_pointer <= read_pointer + 1;
                end
                if (in_put) begin
                    write_pointer <= write_pointer + 1;
                end
            end
        end
    end
endmodule

fifo/tb_fifo_controller.v
module tb_fifo_controller();

    localparam FIFO_ASIZE = 4;              
    localparam DEPTH = (1 << FIFO_ASIZE);

    reg  in_clock = 0;
    reg  in_reset = 0;
    reg  in_take  = 0;
    reg  in_put   = 0;

    wire out_empty;
    wire out_full;
    wire [FIFO_ASIZE-1:0] out_write_pointer;
    wire [FIFO_ASIZE-1:0] out_read_pointer;

    fifo_controller #(
        .FIFO_ASIZE(FIFO_ASIZE)
    ) dut (
        .in_clock(in_clock),
        .in_reset(in_reset),
        .in_take(in_take),
        .in_put(in_put),
        .out_empty(out_empty),
        .out_full(out_full),
        .out_write_pointer(out_write_pointer),
        .out_read_pointer(out_read_pointer)
    );

    always #5 in_clock = ~in_clock;

    task step(input put, input take);
    begin
        in_put  = put;
        in_take = take;
        #10;
    end
    endtask

    integer i;

    initial begin
        $dumpfile("tb_fifo_controller.vcd");
        $dumpvars(0, tb_fifo_controller);

        in_reset = 1;
        step(0,0);
        step(0,0);
        in_reset = 0;

        //TAKE when EMPTY (should NOT move read pointer)
        step(0,1);
        step(0,0);

        //PUT when EMPTY (should write one entry)
        step(1,0);
        step(0,0);

        //PUT+TAKE when AVAIL
        step(1,1);
        step(0,0);

        //TAKE only in AVAIL
        step(0,1);
        step(0,0);

        //Drain until EMPTY (extra TAKE attempts too)
        for (i = 0; i < 3; i = i + 1)
            step(0,1);
        step(0,0);

        //now empty again -> take should do nothing
        step(0,1);
        step(0,0);

        //Fill FIFO until FULL
        for (i = 0; i < DEPTH; i = i + 1)
            step(1,0);
        step(0,0);

        //PUT when FULL (should do nothing)
        step(1,0);
        step(0,0);

        //TAKE when FULL (should start freeing space)
        step(0,1);
        step(0,0);

        //PUT+TAKE while not empty/not full (AVAIL)
        for (i = 0; i < 5; i = i + 1)
            step(1,1);
        step(0,0);

        #50; $finish;
end

endmodule

fifo/tb_fifo_controller.vcd
$date
	Sun Feb  1 21:42:26 2026
$end
$version
	Icarus Verilog
$end
$timescale
	1s
$end
$scope module tb_fifo_controller $end
$var wire 4 ! out_write_pointer [3:0] $end
$var wire 4 " out_read_pointer [3:0] $end
$var wire 1 # out_full $end
$var wire 1 $ out_empty $end
$var parameter 36 % DEPTH $end
$var parameter 32 & FIFO_ASIZE $end
$var reg 1 ' in_clock $end
$var reg 1 ( in_put $end
$var reg 1 ) in_reset $end
$var reg 1 * in_take $end
$var integer 32 + i [31:0] $end
$scope module dut $end
$var wire 1 ' in_clock $end
$var wire 1 ( in_put $end
$var wire 1 ) in_reset $end
$var wire 1 * in_take $end
$var wire 1 # out_full $end
$var wire 4 , out_write_pointer [3:0] $end
$var wire 4 - out_read_pointer [3:0] $end
$var wire 1 $ out_empty $end
$var parameter 32 . FIFO_ASIZE $end
$var reg 5 / read_pointer [4:0] $end
$var reg 5 0 write_pointer [4:0] $end
$upscope $end
$scope task step $end
$var reg 1 1 put $end
$var reg 1 2 take $end
$upscope $end
$upscope $end
$enddefinitions $end
$comment Show the parameter values. $end
$dumpall
b100 .
b100 &
b10000 %
$end
#0
$dumpvars
02
01
bx 0
bx /
bx -
bx ,
bx +
0*
1)
0(
0'
x$
x#
bx "
bx !
$end
#5
0#
b0 !
b0 ,
b0 "
b0 -
1$
b0 0
b0 /
1'
#10
0'
#15
1'
#20
0'
1*
12
0)
#25
1'
#30
0'
0*
02
#35
1'
#40
0'
1(
11
#45
b1 !
b1 ,
0$
b1 0
1'
#50
0'
0(
01
#55
1'
#60
0'
1*
1(
12
11
#65
b10 !
b10 ,
b1 "
b1 -
b10 0
0$
b1 /
1'
#70
0'
0*
0(
02
01
#75
1'
#80
0'
1*
12
#85
b10 "
b10 -
1$
b10 /
1'
#90
0'
0*
02
#95
1'
#100
0'
1*
12
b0 +
#105
1'
#110
0'
b1 +
#115
1'
#120
0'
b10 +
#125
1'
#130
0'
0*
02
b11 +
#135
1'
#140
0'
1*
12
#145
1'
#150
0'
0*
02
#155
1'
#160
0'
1(
11
b0 +
#165
b11 !
b11 ,
0$
b11 0
1'
#170
0'
b1 +
#175
b100 !
b100 ,
b100 0
1'
#180
0'
b10 +
#185
b101 !
b101 ,
b101 0
1'
#190
0'
b11 +
#195
b110 !
b110 ,
b110 0
1'
#200
0'
b100 +
#205
b111 !
b111 ,
b111 0
1'
#210
0'
b101 +
#215
b1000 !
b1000 ,
b1000 0
1'
#220
0'
b110 +
#225
b1001 !
b1001 ,
b1001 0
1'
#230
0'
b111 +
#235
b1010 !
b1010 ,
b1010 0
1'
#240
0'
b1000 +
#245
b1011 !
b1011 ,
b1011 0
1'
#250
0'
b1001 +
#255
b1100 !
b1100 ,
b1100 0
1'
#260
0'
b1010 +
#265
b1101 !
b1101 ,
b1101 0
1'
#270
0'
b1011 +
#275
b1110 !
b1110 ,
b1110 0
1'
#280
0'
b1100 +
#285
b1111 !
b1111 ,
b1111 0
1'
#290
0'
b1101 +
#295
b0 !
b0 ,
b10000 0
1'
#300
0'
b1110 +
#305
b1 !
b1 ,
b10001 0
1'
#310
0'
b1111 +
#315
1#
b10 !
b10 ,
b10010 0
1'
#320
0'
0(
01
b10000 +
#325
1'
#330
0'
1(
11
#335
1'
#340
0'
0(
01
#345
1'
#350
0'
1*
12
#355
0#
b11 "
b11 -
b11 /
1'
#360
0'
0*
02
#365
1'
#370
0'
1*
1(
12
11
b0 +
#375
b11 !
b11 ,
b100 "
b100 -
b10011 0
b100 /
1'
#380
0'
b1 +
#385
b100 !
b100 ,
b101 "
b101 -
b10100 0
b101 /
1'
#390
0'
b10 +
#395
b101 !
b101 ,
b110 "
b110 -
b10101 0
b110 /
1'
#400
0'
b11 +
#405
b110 !
b110 ,
b111 "
b111 -
b10110 0
b111 /
1'
#410
0'
b100 +
#415
b111 !
b111 ,
b1000 "
b1000 -
b10111 0
b1000 /
1'
#420
0'
0*
0(
02
01
b101 +
