fifo/fifo.v
module fifo #(
    parameter DATA_WIDTH = 8,
    parameter FIFO_ASIZE = 4
)(
    input wire in_clock,
    input wire in_reset,
    input wire in_take,
    input wire in_put,
    output wire out_empty,
    output wire out_full,
    output wire [DATA_WIDTH-1:0] out_data,
    input wire [DATA_WIDTH-1:0] in_data
);
    wire [FIFO_ASIZE-1:0] write_address;
    wire [FIFO_ASIZE-1:0] read_address;

    fifo_controller controller(
        .in_clock(in_clock),
        .in_reset(in_reset),
        .in_put(in_put),
        .in_take(in_take),
        .out_empty(out_empty),
        .out_full(out_full),
        .out_read_pointer(read_address),
        .out_write_pointer(write_address)
    );

    reg [DATA_WIDTH-1:0] memory [0:(1<<FIFO_ASIZE)-1];
    reg [DATA_WIDTH-1:0] data;
    assign out_data = data;

    always @(posedge in_clock) begin
        if (in_reset) begin
            data <= 0;
        end
        else if (in_take && ~out_empty) begin
            data <= memory[read_address];
        end
        else begin
            data <= data;
        end
        if (in_put && ~out_full) begin
            memory[write_address] <= in_data;
        end

    end
endmodule

module fifo_controller #(
    parameter FIFO_ASIZE = 4
)(
    input wire in_clock,
    input wire in_reset,
    input wire in_take,
    input wire in_put,
    output wire out_empty,
    output wire out_full,
    output wire [FIFO_ASIZE-1:0] out_write_pointer,
    output wire [FIFO_ASIZE-1:0] out_read_pointer
);
    reg [FIFO_ASIZE:0] read_pointer;
    reg [FIFO_ASIZE:0] write_pointer; // write pointer can go back to begin when memory is full, then the extra bit indicates it went back

    assign out_write_pointer = write_pointer[FIFO_ASIZE-1:0];
    assign out_read_pointer  = read_pointer[FIFO_ASIZE-1:0];

    assign out_empty = (read_pointer == write_pointer); // read pointer catches write pointer, higher addresses are not written or already read, write is allowed
    assign out_full = (read_pointer[FIFO_ASIZE-1:0] == write_pointer[FIFO_ASIZE-1:0]) // read pointer went back to begin, so higher addresses are unread and cannot be overwritten
                && (read_pointer[FIFO_ASIZE] != write_pointer[FIFO_ASIZE]);

    always @(posedge in_clock) begin
        if (in_reset) begin // reset case
            read_pointer <= 0;
            write_pointer <= 0;
        end
        else begin
            if (out_empty) begin // empty case: only in_put or both is allowed
                if (in_put && ~in_take) begin
                    write_pointer <= write_pointer + 1;
                end
                else if (in_put && in_take) begin
                    write_pointer <= write_pointer + 1;
                    read_pointer <= read_pointer + 1;
                end
            end
            else if (out_full) begin // full case: only in_take or both is allowed
                if (in_take & ~in_put) begin 
                    read_pointer <= read_pointer + 1;
                end
                else if (in_put & in_take) begin
                    write_pointer <= write_pointer + 1;
                    read_pointer <= read_pointer + 1;
                end
            end
            else begin // normal case: everything is allowed
                if (in_take) begin
                    read_pointer <= read_pointer + 1;
                end
                if (in_put) begin
                    write_pointer <= write_pointer + 1;
                end
            end
        end
    end
endmodule

fifo/tb_fifo.v
module tb_fifo;

    localparam DATA_WIDTH = 8;
    localparam FIFO_ASIZE = 4;
    localparam DEPTH = (1 << FIFO_ASIZE);

    reg  in_clock = 0;
    reg  in_reset = 0;
    reg  in_put = 0;
    reg  in_take = 0;
    reg  [DATA_WIDTH-1:0] in_data = 0;

    wire out_empty;
    wire out_full;
    wire [DATA_WIDTH-1:0] out_data;

    fifo #(
        .DATA_WIDTH(DATA_WIDTH),
        .FIFO_ASIZE(FIFO_ASIZE)
    ) DUT (
        .in_clock(in_clock),
        .in_reset(in_reset),
        .in_put(in_put),
        .in_take(in_take),
        .in_data(in_data),
        .out_data(out_data),
        .out_empty(out_empty),
        .out_full(out_full)
    );

    always #5 in_clock = ~in_clock;

    task step(input put, input take, input [DATA_WIDTH-1:0] data);
    begin
        in_put  = put;
        in_take = take;
        in_data = data;
        #10;
    end
    endtask

    integer i;

    initial begin
        $dumpfile("tb_fifo.vcd");
        $dumpvars(0, tb_fifo);

        // -------- RESET --------
        in_reset = 1;
        step(0,0,0);
        in_reset = 0;
        step(0,0,0);

        step(1,0,8'hAA); // put 0xAA
        step(0,0,0);

        step(0,1,0); // take
        step(0,0,0);

        for (i = 0; i < DEPTH; i = i + 1) // fill to full
            step(1,0,i);
        step(0,0,0);

        step(1,0,8'hFF); //put when full 
        step(0,0,0);

        for (i = 0; i < 3; i = i + 1)
            step(0,1,0);
        step(0,0,0);

        step(1,1,8'h55); //put+take
        step(0,0,0);

        #50; $finish;
    end

endmodule

fifo/tb_fifo.vcd
$date
	Sun Feb  1 22:38:59 2026
$end
$version
	Icarus Verilog
$end
$timescale
	1s
$end
$scope module tb_fifo $end
$var wire 1 ! out_full $end
$var wire 1 " out_empty $end
$var wire 8 # out_data [7:0] $end
$var parameter 32 $ DATA_WIDTH $end
$var parameter 36 % DEPTH $end
$var parameter 32 & FIFO_ASIZE $end
$var reg 1 ' in_clock $end
$var reg 8 ( in_data [7:0] $end
$var reg 1 ) in_put $end
$var reg 1 * in_reset $end
$var reg 1 + in_take $end
$var integer 32 , i [31:0] $end
$scope module DUT $end
$var wire 1 ' in_clock $end
$var wire 8 - in_data [7:0] $end
$var wire 1 ) in_put $end
$var wire 1 * in_reset $end
$var wire 1 + in_take $end
$var wire 8 . out_data [7:0] $end
$var wire 4 / write_address [3:0] $end
$var wire 4 0 read_address [3:0] $end
$var wire 1 ! out_full $end
$var wire 1 " out_empty $end
$var parameter 32 1 DATA_WIDTH $end
$var parameter 32 2 FIFO_ASIZE $end
$var reg 8 3 data [7:0] $end
$scope module controller $end
$var wire 1 ' in_clock $end
$var wire 1 ) in_put $end
$var wire 1 * in_reset $end
$var wire 1 + in_take $end
$var wire 1 ! out_full $end
$var wire 4 4 out_write_pointer [3:0] $end
$var wire 4 5 out_read_pointer [3:0] $end
$var wire 1 " out_empty $end
$var parameter 32 6 FIFO_ASIZE $end
$var reg 5 7 read_pointer [4:0] $end
$var reg 5 8 write_pointer [4:0] $end
$upscope $end
$upscope $end
$scope task step $end
$var reg 8 9 data [7:0] $end
$var reg 1 : put $end
$var reg 1 ; take $end
$upscope $end
$upscope $end
$enddefinitions $end
$comment Show the parameter values. $end
$dumpall
b100 6
b100 2
b1000 1
b100 &
b10000 %
b1000 $
$end
#0
$dumpvars
0;
0:
b0 9
bx 8
bx 7
bx 5
bx 4
bx 3
bx 0
bx /
bx .
b0 -
bx ,
0+
1*
0)
b0 (
0'
bx #
x"
x!
$end
#5
0!
b0 /
b0 4
b0 0
b0 5
1"
b0 8
b0 7
b0 #
b0 .
b0 3
1'
#10
0'
0*
#15
1'
#20
0'
b10101010 (
b10101010 -
1)
b10101010 9
1:
#25
b1 /
b1 4
0"
b1 8
1'
#30
0'
b0 (
b0 -
0)
b0 9
0:
#35
1'
#40
0'
1+
1;
#45
b1 0
b1 5
1"
b1 7
b10101010 #
b10101010 .
b10101010 3
1'
#50
0'
0+
0;
#55
1'
#60
0'
1)
1:
b0 ,
#65
b10 /
b10 4
0"
b10 8
1'
#70
0'
b1 (
b1 -
b1 9
b1 ,
#75
b11 /
b11 4
b11 8
1'
#80
0'
b10 (
b10 -
b10 9
b10 ,
#85
b100 /
b100 4
b100 8
1'
#90
0'
b11 (
b11 -
b11 9
b11 ,
#95
b101 /
b101 4
b101 8
1'
#100
0'
b100 (
b100 -
b100 9
b100 ,
#105
b110 /
b110 4
b110 8
1'
#110
0'
b101 (
b101 -
b101 9
b101 ,
#115
b111 /
b111 4
b111 8
1'
#120
0'
b110 (
b110 -
b110 9
b110 ,
#125
b1000 /
b1000 4
b1000 8
1'
#130
0'
b111 (
b111 -
b111 9
b111 ,
#135
b1001 /
b1001 4
b1001 8
1'
#140
0'
b1000 (
b1000 -
b1000 9
b1000 ,
#145
b1010 /
b1010 4
b1010 8
1'
#150
0'
b1001 (
b1001 -
b1001 9
b1001 ,
#155
b1011 /
b1011 4
b1011 8
1'
#160
0'
b1010 (
b1010 -
b1010 9
b1010 ,
#165
b1100 /
b1100 4
b1100 8
1'
#170
0'
b1011 (
b1011 -
b1011 9
b1011 ,
#175
b1101 /
b1101 4
b1101 8
1'
#180
0'
b1100 (
b1100 -
b1100 9
b1100 ,
#185
b1110 /
b1110 4
b1110 8
1'
#190
0'
b1101 (
b1101 -
b1101 9
b1101 ,
#195
b1111 /
b1111 4
b1111 8
1'
#200
0'
b1110 (
b1110 -
b1110 9
b1110 ,
#205
b0 /
b0 4
b10000 8
1'
#210
0'
b1111 (
b1111 -
b1111 9
b1111 ,
#215
1!
b1 /
b1 4
b10001 8
1'
#220
0'
b0 (
b0 -
0)
b0 9
0:
b10000 ,
#225
1'
#230
0'
b11111111 (
b11111111 -
1)
b11111111 9
1:
#235
1'
#240
0'
b0 (
b0 -
0)
b0 9
0:
#245
1'
#250
0'
1+
1;
b0 ,
#255
0!
b10 0
b10 5
b0 #
b0 .
b0 3
b10 7
1'
#260
0'
b1 ,
#265
b11 0
b11 5
b11 7
b1 #
b1 .
b1 3
1'
#270
0'
b10 ,
#275
b100 0
b100 5
b10 #
b10 .
b10 3
b100 7
1'
#280
0'
0+
0;
b11 ,
#285
1'
#290
0'
b1010101 (
b1010101 -
1+
1)
b1010101 9
1;
1:
#295
b10 /
b10 4
b101 0
b101 5
b11 #
b11 .
b11 3
b10010 8
b101 7
1'
#300
0'
b0 (
b0 -
0+
0)
b0 9
0;
0:
