multiplexer/multiplexer.v
module multiplexer(
    input wire I1,
    input wire I2,
    input wire I3,
    input wire I0,
    input wire [1:0] S,
    output wire O
);
    assign O = (I0&(~S[0])&(~S[1]) | (I1&(S[0])&(~S[1])) | (I2&(~S[0])&(S[1])) | (I3&(S[0])&(S[1])));
endmodule

multiplexer/tb_multiplexer.v
module tb_multiplexer();
    reg I0 = 0;
    reg I1 = 0;
    reg I2 = 0;
    reg I3 = 0;
    reg [1:0] S = 2'b00;
    wire out;

    multiplexer DUT(
        .I0(I0),
        .I1(I1),
        .I2(I2),
        .I3(I3),
        .S(S),
        .O(O)
    );

    initial begin 
        $dumpfile("tb_multiplexer.vcd");
        $dumpvars(0, tb_multiplexer);

        #3; I0 = 1;
        #3; I0 = 0; I1 = 1;
        #3; S = 2'b01;
        #3; S = 2'b10;
        #2; I2 = 1;
        #1; S = 3'b11;
        #1; I3 = 1;
        #5; $finish;
    end
endmodule

multiplexer/tb_multiplexer.vcd
$date
	Fri Jan 30 14:56:16 2026
$end
$version
	Icarus Verilog
$end
$timescale
	1s
$end
$scope module tb_multiplexer $end
$var wire 1 ! O $end
$var reg 1 " I0 $end
$var reg 1 # I1 $end
$var reg 1 $ I2 $end
$var reg 1 % I3 $end
$var reg 2 & S [1:0] $end
$scope module DUT $end
$var wire 1 " I0 $end
$var wire 1 # I1 $end
$var wire 1 $ I2 $end
$var wire 1 % I3 $end
$var wire 1 ! O $end
$var wire 2 ' S [1:0] $end
$upscope $end
$upscope $end
$enddefinitions $end
$comment Show the parameter values. $end
$dumpall
$end
#0
$dumpvars
b0 '
b0 &
0%
0$
0#
0"
0!
$end
#3
1!
1"
#6
0!
1#
0"
#9
1!
b1 &
b1 '
#12
0!
b10 &
b10 '
#14
1!
1$
#15
0!
b11 &
b11 '
#16
1!
1%
