edge_counter/edge_counter.v
module edge_detector(
    input wire in_clock,
    input wire in_signal,
    output wire out_strobe
    );
    reg past = 0;

    always @(posedge in_clock)
    begin
        past <= in_signal;
    end

    assign out_strobe = ~past & in_signal;
endmodule

module counter (
    input wire in_clock,
    input wire in_reset,
    input wire in_enable,
    output reg[7:0] out_value
);
    always @(posedge in_clock) begin
        if (in_reset) begin
            out_value <= 8'b00000000;
        end
        else if (in_enable) begin
            out_value <= out_value + 1;
        end
    end
endmodule

module edge_counter(
    input wire in_clock,
    input wire in_reset,
    input wire in_signal,
    output wire out_pulse,
    output wire [7:0] out_count
);

    edge_detector detector(
        .in_clock(in_clock),
        .in_signal(in_signal),
        .out_strobe(out_pulse)
    );

    counter count(
        .in_clock(in_clock),
        .in_reset(in_reset),
        .in_enable(out_pulse),
        .out_value(out_count)
    );

endmodule

edge_counter/tb_edge_counter.v
module tb_edge_counter();
    reg clock = 1;
    reg signal = 1;
    reg reset = 1;
    wire pulse;
    wire [7:0] count;

    always #5 clock <= ~clock;

    edge_counter DUT(
        .in_clock(clock),
        .in_reset(reset),
        .in_signal(signal),
        .out_pulse(pulse),
        .out_count(count)
    );

    initial begin
        $dumpfile("tb_edge_counter.vcd");
        $dumpvars(0, tb_edge_counter);
        #11; reset = 0; signal = 0;
        #20; signal = 1;
        #10; signal = 0;
        #30; signal = 1;
        #50; signal = 0; 
        #10; signal = 1; reset = 1;
        #30; $finish;
    end
endmodule

edge_counter/tb_edge_counter.vcd
$date
	Sat Jan 31 12:25:05 2026
$end
$version
	Icarus Verilog
$end
$timescale
	1s
$end
$scope module tb_edge_counter $end
$var wire 1 ! pulse $end
$var wire 8 " count [7:0] $end
$var reg 1 # clock $end
$var reg 1 $ reset $end
$var reg 1 % signal $end
$scope module DUT $end
$var wire 1 # in_clock $end
$var wire 1 $ in_reset $end
$var wire 1 % in_signal $end
$var wire 1 ! out_pulse $end
$var wire 8 & out_count [7:0] $end
$scope module count $end
$var wire 1 # in_clock $end
$var wire 1 $ in_reset $end
$var wire 1 ! in_enable $end
$var reg 8 ' out_value [7:0] $end
$upscope $end
$scope module detector $end
$var wire 1 # in_clock $end
$var wire 1 % in_signal $end
$var wire 1 ! out_strobe $end
$var reg 1 ( past $end
$upscope $end
$upscope $end
$upscope $end
$enddefinitions $end
$comment Show the parameter values. $end
$dumpall
$end
#0
$dumpvars
1(
b0 '
b0 &
1%
1$
1#
b0 "
0!
$end
#5
0#
#10
1#
#11
0%
0$
#15
0#
#20
0(
1#
#25
0#
#30
1#
#31
1!
1%
#35
0#
#40
0!
1(
b1 "
b1 &
b1 '
1#
#41
0%
#45
0#
#50
0(
1#
#55
0#
#60
1#
#65
0#
#70
1#
#71
1!
1%
#75
0#
#80
0!
1(
b10 "
b10 &
b10 '
1#
#85
0#
#90
1#
#95
0#
#100
1#
#105
0#
#110
1#
#115
0#
#120
1#
#121
0%
#125
0#
#130
0(
1#
#131
1!
1$
1%
#135
0#
#140
0!
1(
b0 "
b0 &
b0 '
1#
