decoder/decoder.v
module decoder #(
    parameter NUM_OUTPUT = 4
) (
    input wire [$clog2(NUM_OUTPUT)-1:0] in_address,
    output wire [NUM_OUTPUT-1:0] out_select,
    output wire out_error
);

    assign out_error = (in_address >= NUM_OUTPUT); //out_select max index is NUM_OUTPUT - 1, which is the maximum of in_address
    assign out_select = (out_error & 0) | (~out_error & (1 <<  in_address));

endmodule

decoder/tb_decoder.v
module tb_decoder ();
    parameter num = 5;
    reg [$clog2(num)-1:0] address = 0;
    wire [num-1:0] select;
    wire error;

    decoder #(.NUM_OUTPUT(num)) DUT (
        .in_address(address),
        .out_select(select),
        .out_error(error)
    );

    initial begin 
        $dumpfile("tb_decoder.vcd");
        $dumpvars(0, tb_decoder);
        #5; address = 1;
        #5; address = 2;
        #5; address = 3;
        #5; address = 4;
        #5; address = 5;
        #5; address = 6;
        #5; address = 7;
        #5; $finish;
    end
endmodule

decoder/tb_decoder.vcd
$date
	Sat Jan 31 02:35:50 2026
$end
$version
	Icarus Verilog
$end
$timescale
	1s
$end
$scope module tb_decoder $end
$var wire 5 ! select [4:0] $end
$var wire 1 " error $end
$var parameter 32 # num $end
$var reg 3 $ address [2:0] $end
$scope module DUT $end
$var wire 3 % in_address [2:0] $end
$var wire 5 & out_select [4:0] $end
$var wire 1 " out_error $end
$var parameter 32 ' NUM_OUTPUT $end
$upscope $end
$upscope $end
$enddefinitions $end
$comment Show the parameter values. $end
$dumpall
b101 '
b101 #
$end
#0
$dumpvars
b1 &
b0 %
b0 $
0"
b1 !
$end
#5
b10 !
b10 &
b1 $
b1 %
#10
b100 !
b100 &
b10 $
b10 %
#15
b1000 !
b1000 &
b11 $
b11 %
#20
b10000 !
b10000 &
b100 $
b100 %
#25
b0 !
b0 &
1"
b101 $
b101 %
#30
b110 $
b110 %
#35
b111 $
b111 %
